preetitouicode/__init__.py
preetitouicode/converter.py
preetitouicode-0.1.0.dist-info/METADATA
preetitouicode-0.1.0.dist-info/WHEEL
preetitouicode-0.1.0.dist-info/top_level.txt
preetitouicode-0.1.0.dist-info/RECORD
