Metadata-Version: 2.1
Name: preetitouicode
Version: 0.1.0
Summary: A Python package to convert Preeti encoded text to Unicode.
Home-page: https://github.com/bimarsha123/preetitounicode
Author: Bimarsha Mishra
Author-email: bimarsha.mishra@gmail.com
Classifier: Programming Language :: Python :: 3
Classifier: License :: OSI Approved :: MIT License
Classifier: Operating System :: OS Independent
Requires-Python: >=3.6
